normedtuple/__init__.py
normedtuple/core/__init__.py
normedtuple/tests/__init__.py
normedtuple/tests/test_0.py
normedtuple/tests/test_qual.py
normedtuple-1.0.2.dist-info/licenses/LICENSE.txt
normedtuple-1.0.2.dist-info/METADATA
normedtuple-1.0.2.dist-info/WHEEL
normedtuple-1.0.2.dist-info/top_level.txt
normedtuple-1.0.2.dist-info/RECORD
